roxbot/__init__.py
roxbot/cli.py
roxbot/config.py
roxbot/exceptions.py
roxbot/interfaces.py
roxbot/node.py
roxbot/nodes.py
roxbot/py.typed
roxbot/vectors.py
roxbot/adapters/__init__.py
roxbot/adapters/mqtt_adapter.py
roxbot/adapters/mqtt_logger.py
roxbot/gps/__init__.py
roxbot/gps/converters.py
roxbot/gps/gps_node.py
roxbot/gps/mock_gps_node.py
roxbot/models/__init__.py
roxbot/models/diff_drive.py
roxbot/models/linear_model.py
roxbot/models/wheels.py
roxbot/utils/__init__.py
roxbot/utils/mock_robot.py
roxbot/utils/runners.py
roxbot-4.1.0.dist-info/LICENSE
roxbot-4.1.0.dist-info/METADATA
roxbot-4.1.0.dist-info/WHEEL
roxbot-4.1.0.dist-info/entry_points.txt
roxbot-4.1.0.dist-info/top_level.txt
roxbot-4.1.0.dist-info/RECORD
