Metadata-Version: 2.1
Name: roxbot
Version: 4.1.0
Summary: Pythonic robotics toolkit
Author-email: ROX Automation <dev@roxautomation.com>
License: MIT
Project-URL: Homepage, https://example.com/roxbot
Classifier: Development Status :: 3 - Alpha
Classifier: Intended Audience :: Developers
Classifier: Operating System :: OS Independent
Classifier: Programming Language :: Python
Classifier: Programming Language :: Python :: 3.11
Classifier: Topic :: Software Development :: Libraries :: Python Modules
Classifier: Typing :: Typed
Requires-Python: >=3.11
License-File: LICENSE
Requires-Dist: aiomqtt
Requires-Dist: click
Requires-Dist: coloredlogs
Requires-Dist: orjson
Requires-Dist: pydantic-settings
Requires-Dist: pydantic
Requires-Dist: rox-vectors
Requires-Dist: pymap3d
Provides-Extra: dev
Requires-Dist: pylint; extra == "dev"
Requires-Dist: mypy; extra == "dev"
Requires-Dist: pytest; extra == "dev"
Requires-Dist: pytest-cov; extra == "dev"
Requires-Dist: pytest-asyncio; extra == "dev"
